{"legislative_session": "2025-2028", "identifier": "PS1131", "title": "Para prohibir la venta, expendio, distribuci\u00f3n, posesi\u00f3n, consumo, publicidad y\nsuministro de todo producto que contenga tianeptina, bajo cualquier nombre\ncomercial, incluyendo, pero sin limitarse a, ZaZa, Tianaa, Pegasus, Red Dawn y\nNeptune\u2019s Fix, o cualquier otro similar; otorgar a los departamentos de Asuntos al\nConsumidor (DACO); y de Salud, la responsabilidad de fiscalizar la aplicaci\u00f3n de\nesta Ley; establecer multas y autorizar la confiscaci\u00f3n de dichos productos; y para\notros fines relacionados.", "from_organization": "~{\"classification\": \"upper\"}", "classification": ["bill"], "subject": [], "abstracts": [], "other_titles": [], "other_identifiers": [], "actions": [{"description": "Radicado", "date": "2026-03-10T04:00:00+00:00", "organization_id": "~{\"classification\": \"legislature\"}", "classification": ["introduction"], "related_entities": []}], "sponsorships": [{"name": "Nitza  Moran Trinidad - Sistema \u00danico de Tr\u00e1mite Legislativo", "classification": "primary", "entity_type": "person", "primary": true, "person_id": "~{\"name\": \"Nitza  Moran Trinidad - Sistema \\u00danico de Tr\\u00e1mite Legislativo\"}", "organization_id": null}], "related_bills": [], "versions": [{"note": "Radicado", "links": [{"url": "https://sutra.oslpr.org/SutraFilesGen/160680/ps1131-26.pdf", "media_type": "application/pdf"}], "date": "2026-03-10", "classification": ""}], "documents": [], "citations": [], "sources": [{"url": "https://sutra.oslpr.org/medidas/160680", "note": ""}], "extras": {}, "jurisdiction": {"id": "ocd-jurisdiction/country:us/territory:pr/government", "name": "Puerto Rico", "classification": "state", "division_id": "ocd-division/country:us/territory:pr"}, "scraped_at": "2026-03-11T09:05:23+00:00", "_id": "7028d742-1d29-11f1-86c6-fa425f02f220"}