{"legislative_session": "2025-2028", "identifier": "RCC0353", "title": "Para ordenar al Superintendente de la Polic\u00eda de Puerto Rico a establecer un periodo de amnist\u00eda de sesenta (60) d\u00edas para la entrega voluntaria de armas de fuego ilegales, legales, heredadas, pertenecientes a personas fallecidas, o con licencias vencidas; establecer mecanismos claros de recopilaci\u00f3n, an\u00e1lisis y divulgaci\u00f3n de datos que permitan medir su impacto real sobre la seguridad p\u00fablica; disponer para la publicidad; presentaci\u00f3n de informes; establecer que no se procesar\u00e1n criminalmente a las personas que entreguen armas de fuego; y para otros fines relacionados.", "from_organization": "~{\"classification\": \"upper\"}", "classification": ["resolution"], "subject": [], "abstracts": [], "other_titles": [], "other_identifiers": [{"identifier": "ocd-bill-pr-2025_2028-rcc353"}], "actions": [{"description": "Radicado", "date": "2026-05-14T04:00:00+00:00", "organization_id": "~{\"classification\": \"legislature\"}", "classification": ["introduction"], "related_entities": []}, {"description": "Aparece en Primera Lectura de la C\u00e1mara", "date": "2026-05-18T04:00:00+00:00", "organization_id": "~{\"classification\": \"lower\"}", "classification": ["reading-1"], "related_entities": []}, {"description": "Referido a Comisi\u00f3n(es)", "date": "2026-05-18T04:00:00+00:00", "organization_id": "~{\"classification\": \"legislature\"}", "classification": ["referral-committee"], "related_entities": []}], "sponsorships": [{"name": "F\u00e9lix E. Pacheco  Burgos - Sistema \u00danico de Tr\u00e1mite Legislativo", "classification": "primary", "entity_type": "person", "primary": true, "person_id": "~{\"name\": \"F\\u00e9lix E. Pacheco  Burgos - Sistema \\u00danico de Tr\\u00e1mite Legislativo\"}", "organization_id": null}], "related_bills": [], "versions": [{"note": "Radicado", "links": [{"url": "https://sutra.oslpr.org/SutraFilesGen/161247/RCC0353.doc", "media_type": "application/msword"}], "date": "2026-05-14", "classification": ""}], "documents": [], "citations": [], "sources": [{"url": "https://sutra.oslpr.org/medidas/161247", "note": ""}], "extras": {}, "jurisdiction": {"id": "ocd-jurisdiction/country:us/territory:pr/government", "name": "Puerto Rico", "classification": "state", "division_id": "ocd-division/country:us/territory:pr"}, "scraped_at": "2026-06-06T10:29:08+00:00", "_id": "8d1d8c1e-6192-11f1-8ee0-7a8f7c4cf62d"}